osc_trino_acl_dsl/__about__.py
osc_trino_acl_dsl/__init__.py
osc_trino_acl_dsl/dsl2rules.py
osc_trino_acl_dsl/rules_precommit_check.py
osc_trino_acl_dsl/jsonschema/__init__.py
osc_trino_acl_dsl/jsonschema/dsl-schema.json
osc_trino_acl_dsl-0.3.1.dist-info/LICENSE
osc_trino_acl_dsl-0.3.1.dist-info/METADATA
osc_trino_acl_dsl-0.3.1.dist-info/WHEEL
osc_trino_acl_dsl-0.3.1.dist-info/entry_points.txt
osc_trino_acl_dsl-0.3.1.dist-info/top_level.txt
osc_trino_acl_dsl-0.3.1.dist-info/RECORD
