Metadata-Version: 2.1
Name: osc-trino-acl-dsl
Version: 0.3.1
Summary: A DSL for generating rules.json files for Trino
Home-page: https://github.com/os-climate/osc-trino-acl-dsl
Author: OS-Climate
Author-email: eje@redhat.com
License: Apache-2.0
Platform: UNKNOWN
Classifier: License :: OSI Approved :: Apache Software License
Classifier: Programming Language :: Python
Classifier: Programming Language :: Python :: 3
Classifier: Programming Language :: Python :: 3 :: Only
Requires-Dist: jsonschema
Requires-Dist: pyyaml
